lazy_toolkit_smb/__init__.py
lazy_toolkit_smb/smb.py
lazy_toolkit_smb-0.0.1.dist-info/LICENSE
lazy_toolkit_smb-0.0.1.dist-info/METADATA
lazy_toolkit_smb-0.0.1.dist-info/WHEEL
lazy_toolkit_smb-0.0.1.dist-info/top_level.txt
lazy_toolkit_smb-0.0.1.dist-info/RECORD
